my_own_package/__init__.py
Bodea_Bogdan-0.2.0.dist-info/METADATA
Bodea_Bogdan-0.2.0.dist-info/WHEEL
Bodea_Bogdan-0.2.0.dist-info/top_level.txt
Bodea_Bogdan-0.2.0.dist-info/RECORD
