Metadata-Version: 2.1
Name: Bodea-Bogdan
Version: 0.2.0
Summary: This is my first package!
Home-page: UNKNOWN
Author: Bodea Bogdan
License: UNKNOWN
Platform: UNKNOWN
